{"elements":[],"behaviors":[{"type":"behavior","desc":"\nUse `Polymer.IronCheckedElementBehavior` to implement a custom element\nthat has a `checked` property, which can be used for validation if the\nelement is also `required`. Element instances implementing this behavior\nwill also be registered for use in an `iron-form` element.\n\n","events":[{"desc":"\nFired when the checked state changes.\n\n","jsdoc":{"description":"\nFired when the checked state changes.\n\n","tags":[{"tag":"event","type":null,"description":"iron-change"}],"orig":"*\n       * Fired when the checked state changes.\n       *\n       * @event iron-change\n       "},"name":"iron-change","params":[]}],"jsdoc":{"description":"\nUse `Polymer.IronCheckedElementBehavior` to implement a custom element\nthat has a `checked` property, which can be used for validation if the\nelement is also `required`. Element instances implementing this behavior\nwill also be registered for use in an `iron-form` element.\n\n","tags":[{"tag":"demo","type":null,"name":"demo/index.html","description":""},{"tag":"polymerBehavior","type":null,"name":"Polymer.IronCheckedElementBehavior","description":null}],"orig":"*\n   * Use `Polymer.IronCheckedElementBehavior` to implement a custom element\n   * that has a `checked` property, which can be used for validation if the\n   * element is also `required`. Element instances implementing this behavior\n   * will also be registered for use in an `iron-form` element.\n   *\n   * @demo demo/index.html\n   * @polymerBehavior Polymer.IronCheckedElementBehavior\n   "},"demos":[{"desc":"demo","path":"demo/index.html"}],"symbol":"Polymer.IronCheckedElementBehaviorImpl","is":"Polymer.IronCheckedElementBehavior","properties":[{"name":"checked","type":"Boolean","desc":"\nGets or sets the state, `true` is checked and `false` is unchecked.\n       ","javascriptNode":{"type":"Property","key":{"type":"Identifier","name":"checked","range":[669,676],"loc":{"start":{"line":24,"column":6},"end":{"line":24,"column":13}}},"value":{"type":"ObjectExpression","properties":[{"type":"Property","key":{"type":"Identifier","name":"type","range":[688,692],"loc":{"start":{"line":25,"column":8},"end":{"line":25,"column":12}}},"value":{"type":"Identifier","name":"Boolean","range":[694,701],"loc":{"start":{"line":25,"column":14},"end":{"line":25,"column":21}}},"kind":"init","method":false,"shorthand":false,"computed":false,"range":[688,701],"loc":{"start":{"line":25,"column":8},"end":{"line":25,"column":21}}},{"type":"Property","key":{"type":"Identifier","name":"value","range":[711,716],"loc":{"start":{"line":26,"column":8},"end":{"line":26,"column":13}}},"value":{"type":"Literal","value":false,"raw":"false","range":[718,723],"loc":{"start":{"line":26,"column":15},"end":{"line":26,"column":20}}},"kind":"init","method":false,"shorthand":false,"computed":false,"range":[711,723],"loc":{"start":{"line":26,"column":8},"end":{"line":26,"column":20}}},{"type":"Property","key":{"type":"Identifier","name":"reflectToAttribute","range":[733,751],"loc":{"start":{"line":27,"column":8},"end":{"line":27,"column":26}}},"value":{"type":"Literal","value":true,"raw":"true","range":[753,757],"loc":{"start":{"line":27,"column":28},"end":{"line":27,"column":32}}},"kind":"init","method":false,"shorthand":false,"computed":false,"range":[733,757],"loc":{"start":{"line":27,"column":8},"end":{"line":27,"column":32}}},{"type":"Property","key":{"type":"Identifier","name":"notify","range":[767,773],"loc":{"start":{"line":28,"column":8},"end":{"line":28,"column":14}}},"value":{"type":"Literal","value":true,"raw":"true","range":[775,779],"loc":{"start":{"line":28,"column":16},"end":{"line":28,"column":20}}},"kind":"init","method":false,"shorthand":false,"computed":false,"range":[767,779],"loc":{"start":{"line":28,"column":8},"end":{"line":28,"column":20}}},{"type":"Property","key":{"type":"Identifier","name":"observer","range":[789,797],"loc":{"start":{"line":29,"column":8},"end":{"line":29,"column":16}}},"value":{"type":"Literal","value":"_checkedChanged","raw":"'_checkedChanged'","range":[799,816],"loc":{"start":{"line":29,"column":18},"end":{"line":29,"column":35}}},"kind":"init","method":false,"shorthand":false,"computed":false,"range":[789,816],"loc":{"start":{"line":29,"column":8},"end":{"line":29,"column":35}}}],"range":[678,824],"loc":{"start":{"line":24,"column":15},"end":{"line":30,"column":7}}},"kind":"init","method":false,"shorthand":false,"computed":false,"range":[669,824],"loc":{"start":{"line":24,"column":6},"end":{"line":30,"column":7}},"leadingComments":[{"type":"Block","value":"*\n       * Fired when the checked state changes.\n       *\n       * @event iron-change\n       ","range":[467,564],"loc":{"start":{"line":15,"column":6},"end":{"line":19,"column":9}}},{"type":"Block","value":"*\n       * Gets or sets the state, `true` is checked and `false` is unchecked.\n       ","range":[572,662],"loc":{"start":{"line":21,"column":6},"end":{"line":23,"column":9}}}]},"published":true,"default":false,"reflectToAttribute":"UNKNOWN","notify":true,"observer":"_checkedChanged","observerNode":{"type":"Literal","value":"_checkedChanged","raw":"'_checkedChanged'","range":[799,816],"loc":{"start":{"line":29,"column":18},"end":{"line":29,"column":35}}},"jsdoc":{"description":"\nGets or sets the state, `true` is checked and `false` is unchecked.\n       ","tags":[],"orig":"*\n       * Gets or sets the state, `true` is checked and `false` is unchecked.\n       "}},{"__fromBehavior":"Polymer.IronValidatableBehavior","name":"hasValidator","type":"Function","desc":"\n","javascriptNode":{"type":"Property","key":{"type":"Identifier","name":"hasValidator","range":[1450,1462],"loc":{"start":{"line":72,"column":4},"end":{"line":72,"column":16}}},"value":{"type":"FunctionExpression","id":null,"params":[],"body":{"type":"BlockStatement","body":[{"type":"ReturnStatement","argument":{"type":"BinaryExpression","operator":"!=","left":{"type":"MemberExpression","computed":false,"object":{"type":"ThisExpression","range":[1490,1494],"loc":{"start":{"line":73,"column":13},"end":{"line":73,"column":17}}},"property":{"type":"Identifier","name":"_validator","range":[1495,1505],"loc":{"start":{"line":73,"column":18},"end":{"line":73,"column":28}}},"range":[1490,1505],"loc":{"start":{"line":73,"column":13},"end":{"line":73,"column":28}}},"right":{"type":"Literal","value":null,"raw":"null","range":[1509,1513],"loc":{"start":{"line":73,"column":32},"end":{"line":73,"column":36}}},"range":[1490,1513],"loc":{"start":{"line":73,"column":13},"end":{"line":73,"column":36}}},"range":[1483,1514],"loc":{"start":{"line":73,"column":6},"end":{"line":73,"column":37}}}],"range":[1475,1520],"loc":{"start":{"line":72,"column":29},"end":{"line":74,"column":5}}},"generator":false,"expression":false,"range":[1464,1520],"loc":{"start":{"line":72,"column":18},"end":{"line":74,"column":5}}},"kind":"init","method":false,"shorthand":false,"computed":false,"range":[1450,1520],"loc":{"start":{"line":72,"column":4},"end":{"line":74,"column":5}},"leadingComments":[{"type":"Block","value":"*\n     * @return {boolean} True if the validator `validator` exists.\n     ","range":[1367,1445],"loc":{"start":{"line":69,"column":4},"end":{"line":71,"column":7}}}]},"params":[],"jsdoc":{"description":"\n","tags":[{"tag":"return","type":"boolean","description":"True if the validator `validator` exists."}],"orig":"*\n     * @return {boolean} True if the validator `validator` exists.\n     "},"function":true,"return":{"type":"boolean","desc":"True if the validator `validator` exists."}},{"__fromBehavior":"Polymer.IronValidatableBehavior","name":"invalid","type":"Boolean","desc":"\nTrue if the last call to `validate` is invalid.\n       ","javascriptNode":{"type":"Property","key":{"type":"Identifier","name":"invalid","range":[714,721],"loc":{"start":{"line":36,"column":6},"end":{"line":36,"column":13}}},"value":{"type":"ObjectExpression","properties":[{"type":"Property","key":{"type":"Identifier","name":"notify","range":[733,739],"loc":{"start":{"line":37,"column":8},"end":{"line":37,"column":14}}},"value":{"type":"Literal","value":true,"raw":"true","range":[741,745],"loc":{"start":{"line":37,"column":16},"end":{"line":37,"column":20}}},"kind":"init","method":false,"shorthand":false,"computed":false,"range":[733,745],"loc":{"start":{"line":37,"column":8},"end":{"line":37,"column":20}}},{"type":"Property","key":{"type":"Identifier","name":"reflectToAttribute","range":[755,773],"loc":{"start":{"line":38,"column":8},"end":{"line":38,"column":26}}},"value":{"type":"Literal","value":true,"raw":"true","range":[775,779],"loc":{"start":{"line":38,"column":28},"end":{"line":38,"column":32}}},"kind":"init","method":false,"shorthand":false,"computed":false,"range":[755,779],"loc":{"start":{"line":38,"column":8},"end":{"line":38,"column":32}}},{"type":"Property","key":{"type":"Identifier","name":"type","range":[789,793],"loc":{"start":{"line":39,"column":8},"end":{"line":39,"column":12}}},"value":{"type":"Identifier","name":"Boolean","range":[795,802],"loc":{"start":{"line":39,"column":14},"end":{"line":39,"column":21}}},"kind":"init","method":false,"shorthand":false,"computed":false,"range":[789,802],"loc":{"start":{"line":39,"column":8},"end":{"line":39,"column":21}}},{"type":"Property","key":{"type":"Identifier","name":"value","range":[812,817],"loc":{"start":{"line":40,"column":8},"end":{"line":40,"column":13}}},"value":{"type":"Literal","value":false,"raw":"false","range":[819,824],"loc":{"start":{"line":40,"column":15},"end":{"line":40,"column":20}}},"kind":"init","method":false,"shorthand":false,"computed":false,"range":[812,824],"loc":{"start":{"line":40,"column":8},"end":{"line":40,"column":20}}}],"range":[723,832],"loc":{"start":{"line":36,"column":15},"end":{"line":41,"column":7}}},"kind":"init","method":false,"shorthand":false,"computed":false,"range":[714,832],"loc":{"start":{"line":36,"column":6},"end":{"line":41,"column":7}},"leadingComments":[{"type":"Block","value":"*\n       * True if the last call to `validate` is invalid.\n       ","range":[637,707],"loc":{"start":{"line":33,"column":6},"end":{"line":35,"column":9}}}]},"published":true,"notify":true,"reflectToAttribute":"UNKNOWN","default":false,"jsdoc":{"description":"\nTrue if the last call to `validate` is invalid.\n       ","tags":[],"orig":"*\n       * True if the last call to `validate` is invalid.\n       "}},{"__fromBehavior":"Polymer.IronFormElementBehavior","name":"name","type":"String","desc":"\nThe name of this element.\n       ","javascriptNode":{"type":"Property","key":{"type":"Identifier","name":"name","range":[541,545],"loc":{"start":{"line":27,"column":6},"end":{"line":27,"column":10}}},"value":{"type":"ObjectExpression","properties":[{"type":"Property","key":{"type":"Identifier","name":"type","range":[557,561],"loc":{"start":{"line":28,"column":8},"end":{"line":28,"column":12}}},"value":{"type":"Identifier","name":"String","range":[563,569],"loc":{"start":{"line":28,"column":14},"end":{"line":28,"column":20}}},"kind":"init","method":false,"shorthand":false,"computed":false,"range":[557,569],"loc":{"start":{"line":28,"column":8},"end":{"line":28,"column":20}}}],"range":[547,577],"loc":{"start":{"line":27,"column":12},"end":{"line":29,"column":7}}},"kind":"init","method":false,"shorthand":false,"computed":false,"range":[541,577],"loc":{"start":{"line":27,"column":6},"end":{"line":29,"column":7}},"leadingComments":[{"type":"Block","value":"*\n       * Fired when the element is added to an `iron-form`.\n       *\n       * @event iron-form-element-register\n       ","range":[214,339],"loc":{"start":{"line":12,"column":6},"end":{"line":16,"column":9}}},{"type":"Block","value":"*\n       * Fired when the element is removed from an `iron-form`.\n       *\n       * @event iron-form-element-unregister\n       ","range":[347,478],"loc":{"start":{"line":18,"column":6},"end":{"line":22,"column":9}}},{"type":"Block","value":"*\n       * The name of this element.\n       ","range":[486,534],"loc":{"start":{"line":24,"column":6},"end":{"line":26,"column":9}}}]},"published":true,"jsdoc":{"description":"\nThe name of this element.\n       ","tags":[],"orig":"*\n       * The name of this element.\n       "}},{"name":"observers","type":"Array","javascriptNode":{"type":"Property","key":{"type":"Identifier","name":"observers","range":[1188,1197],"loc":{"start":{"line":49,"column":4},"end":{"line":49,"column":13}}},"value":{"type":"ArrayExpression","elements":[{"type":"Literal","value":"_requiredChanged(required)","raw":"'_requiredChanged(required)'","range":[1207,1235],"loc":{"start":{"line":50,"column":6},"end":{"line":50,"column":34}}}],"range":[1199,1241],"loc":{"start":{"line":49,"column":15},"end":{"line":51,"column":5}}},"kind":"init","method":false,"shorthand":false,"computed":false,"range":[1188,1241],"loc":{"start":{"line":49,"column":4},"end":{"line":51,"column":5}}}},{"__fromBehavior":"Polymer.IronFormElementBehavior","name":"required","type":"Boolean","desc":"\nSet to true to mark the input as required. If used in a form, a\ncustom element that uses this behavior should also use\nPolymer.IronValidatableBehavior and define a custom validation method.\nOtherwise, a `required` element will always be considered valid.\nIt's also strongly recomended to provide a visual style for the element\nwhen it's value is invalid.\n       ","javascriptNode":{"type":"Property","key":{"type":"Identifier","name":"required","range":[1140,1148],"loc":{"start":{"line":47,"column":6},"end":{"line":47,"column":14}}},"value":{"type":"ObjectExpression","properties":[{"type":"Property","key":{"type":"Identifier","name":"type","range":[1160,1164],"loc":{"start":{"line":48,"column":8},"end":{"line":48,"column":12}}},"value":{"type":"Identifier","name":"Boolean","range":[1166,1173],"loc":{"start":{"line":48,"column":14},"end":{"line":48,"column":21}}},"kind":"init","method":false,"shorthand":false,"computed":false,"range":[1160,1173],"loc":{"start":{"line":48,"column":8},"end":{"line":48,"column":21}}},{"type":"Property","key":{"type":"Identifier","name":"value","range":[1183,1188],"loc":{"start":{"line":49,"column":8},"end":{"line":49,"column":13}}},"value":{"type":"Literal","value":false,"raw":"false","range":[1190,1195],"loc":{"start":{"line":49,"column":15},"end":{"line":49,"column":20}}},"kind":"init","method":false,"shorthand":false,"computed":false,"range":[1183,1195],"loc":{"start":{"line":49,"column":8},"end":{"line":49,"column":20}}}],"range":[1150,1203],"loc":{"start":{"line":47,"column":16},"end":{"line":50,"column":7}}},"kind":"init","method":false,"shorthand":false,"computed":false,"range":[1140,1203],"loc":{"start":{"line":47,"column":6},"end":{"line":50,"column":7}},"leadingComments":[{"type":"Block","value":"*\n       * Set to true to mark the input as required. If used in a form, a\n       * custom element that uses this behavior should also use\n       * Polymer.IronValidatableBehavior and define a custom validation method.\n       * Otherwise, a `required` element will always be considered valid.\n       * It's also strongly recomended to provide a visual style for the element\n       * when it's value is invalid.\n       ","range":[711,1133],"loc":{"start":{"line":39,"column":6},"end":{"line":46,"column":9}}}]},"published":true,"default":false,"jsdoc":{"description":"\nSet to true to mark the input as required. If used in a form, a\ncustom element that uses this behavior should also use\nPolymer.IronValidatableBehavior and define a custom validation method.\nOtherwise, a `required` element will always be considered valid.\nIt's also strongly recomended to provide a visual style for the element\nwhen it's value is invalid.\n       ","tags":[],"orig":"*\n       * Set to true to mark the input as required. If used in a form, a\n       * custom element that uses this behavior should also use\n       * Polymer.IronValidatableBehavior and define a custom validation method.\n       * Otherwise, a `required` element will always be considered valid.\n       * It's also strongly recomended to provide a visual style for the element\n       * when it's value is invalid.\n       "}},{"name":"toggles","type":"Boolean","desc":"\nIf true, the button toggles the active state with each tap or press\nof the spacebar.\n       ","javascriptNode":{"type":"Property","key":{"type":"Identifier","name":"toggles","range":[956,963],"loc":{"start":{"line":36,"column":6},"end":{"line":36,"column":13}}},"value":{"type":"ObjectExpression","properties":[{"type":"Property","key":{"type":"Identifier","name":"type","range":[975,979],"loc":{"start":{"line":37,"column":8},"end":{"line":37,"column":12}}},"value":{"type":"Identifier","name":"Boolean","range":[981,988],"loc":{"start":{"line":37,"column":14},"end":{"line":37,"column":21}}},"kind":"init","method":false,"shorthand":false,"computed":false,"range":[975,988],"loc":{"start":{"line":37,"column":8},"end":{"line":37,"column":21}}},{"type":"Property","key":{"type":"Identifier","name":"value","range":[998,1003],"loc":{"start":{"line":38,"column":8},"end":{"line":38,"column":13}}},"value":{"type":"Literal","value":true,"raw":"true","range":[1005,1009],"loc":{"start":{"line":38,"column":15},"end":{"line":38,"column":19}}},"kind":"init","method":false,"shorthand":false,"computed":false,"range":[998,1009],"loc":{"start":{"line":38,"column":8},"end":{"line":38,"column":19}}},{"type":"Property","key":{"type":"Identifier","name":"reflectToAttribute","range":[1019,1037],"loc":{"start":{"line":39,"column":8},"end":{"line":39,"column":26}}},"value":{"type":"Literal","value":true,"raw":"true","range":[1039,1043],"loc":{"start":{"line":39,"column":28},"end":{"line":39,"column":32}}},"kind":"init","method":false,"shorthand":false,"computed":false,"range":[1019,1043],"loc":{"start":{"line":39,"column":8},"end":{"line":39,"column":32}}}],"range":[965,1051],"loc":{"start":{"line":36,"column":15},"end":{"line":40,"column":7}}},"kind":"init","method":false,"shorthand":false,"computed":false,"range":[956,1051],"loc":{"start":{"line":36,"column":6},"end":{"line":40,"column":7}},"leadingComments":[{"type":"Block","value":"*\n       * If true, the button toggles the active state with each tap or press\n       * of the spacebar.\n       ","range":[833,949],"loc":{"start":{"line":32,"column":6},"end":{"line":35,"column":9}}}]},"published":true,"default":true,"reflectToAttribute":"UNKNOWN","jsdoc":{"description":"\nIf true, the button toggles the active state with each tap or press\nof the spacebar.\n       ","tags":[],"orig":"*\n       * If true, the button toggles the active state with each tap or press\n       * of the spacebar.\n       "}},{"__fromBehavior":"Polymer.IronValidatableBehavior","name":"validate","type":"Function","desc":"\nReturns true if the `value` is valid, and updates `invalid`. If you want\nyour element to have custom validation logic, do not override this method;\noverride `_getValidity(value)` instead.\n\n","javascriptNode":{"type":"Property","key":{"type":"Identifier","name":"validate","range":[1957,1965],"loc":{"start":{"line":85,"column":4},"end":{"line":85,"column":12}}},"value":{"type":"FunctionExpression","id":null,"params":[{"type":"Identifier","name":"value","range":[1976,1981],"loc":{"start":{"line":85,"column":23},"end":{"line":85,"column":28}}}],"body":{"type":"BlockStatement","body":[{"type":"ExpressionStatement","expression":{"type":"AssignmentExpression","operator":"=","left":{"type":"MemberExpression","computed":false,"object":{"type":"ThisExpression","range":[1991,1995],"loc":{"start":{"line":86,"column":6},"end":{"line":86,"column":10}}},"property":{"type":"Identifier","name":"invalid","range":[1996,2003],"loc":{"start":{"line":86,"column":11},"end":{"line":86,"column":18}}},"range":[1991,2003],"loc":{"start":{"line":86,"column":6},"end":{"line":86,"column":18}}},"right":{"type":"UnaryExpression","operator":"!","argument":{"type":"CallExpression","callee":{"type":"MemberExpression","computed":false,"object":{"type":"ThisExpression","range":[2007,2011],"loc":{"start":{"line":86,"column":22},"end":{"line":86,"column":26}}},"property":{"type":"Identifier","name":"_getValidity","range":[2012,2024],"loc":{"start":{"line":86,"column":27},"end":{"line":86,"column":39}}},"range":[2007,2024],"loc":{"start":{"line":86,"column":22},"end":{"line":86,"column":39}}},"arguments":[{"type":"Identifier","name":"value","range":[2025,2030],"loc":{"start":{"line":86,"column":40},"end":{"line":86,"column":45}}}],"range":[2007,2031],"loc":{"start":{"line":86,"column":22},"end":{"line":86,"column":46}}},"prefix":true,"range":[2006,2031],"loc":{"start":{"line":86,"column":21},"end":{"line":86,"column":46}}},"range":[1991,2031],"loc":{"start":{"line":86,"column":6},"end":{"line":86,"column":46}}},"range":[1991,2032],"loc":{"start":{"line":86,"column":6},"end":{"line":86,"column":47}}},{"type":"ReturnStatement","argument":{"type":"UnaryExpression","operator":"!","argument":{"type":"MemberExpression","computed":false,"object":{"type":"ThisExpression","range":[2047,2051],"loc":{"start":{"line":87,"column":14},"end":{"line":87,"column":18}}},"property":{"type":"Identifier","name":"invalid","range":[2052,2059],"loc":{"start":{"line":87,"column":19},"end":{"line":87,"column":26}}},"range":[2047,2059],"loc":{"start":{"line":87,"column":14},"end":{"line":87,"column":26}}},"prefix":true,"range":[2046,2059],"loc":{"start":{"line":87,"column":13},"end":{"line":87,"column":26}}},"range":[2039,2060],"loc":{"start":{"line":87,"column":6},"end":{"line":87,"column":27}}}],"range":[1983,2066],"loc":{"start":{"line":85,"column":30},"end":{"line":88,"column":5}}},"generator":false,"expression":false,"range":[1967,2066],"loc":{"start":{"line":85,"column":14},"end":{"line":88,"column":5}}},"kind":"init","method":false,"shorthand":false,"computed":false,"range":[1957,2066],"loc":{"start":{"line":85,"column":4},"end":{"line":88,"column":5}},"leadingComments":[{"type":"Block","value":"*\n     * Returns true if the `value` is valid, and updates `invalid`. If you want\n     * your element to have custom validation logic, do not override this method;\n     * override `_getValidity(value)` instead.\n\n     * @param {Object} value The value to be validated. By default, it is passed\n     * to the validator's `validate()` function, if a validator is set.\n     * @return {boolean} True if `value` is valid.\n     ","range":[1527,1952],"loc":{"start":{"line":76,"column":4},"end":{"line":84,"column":7}}}]},"params":[{"name":"value","type":"Object","desc":"The value to be validated. By default, it is passed\nto the validator's `validate()` function, if a validator is set."}],"jsdoc":{"description":"\nReturns true if the `value` is valid, and updates `invalid`. If you want\nyour element to have custom validation logic, do not override this method;\noverride `_getValidity(value)` instead.\n\n","tags":[{"tag":"param","type":"Object","name":"value","description":"The value to be validated. By default, it is passed\nto the validator's `validate()` function, if a validator is set."},{"tag":"return","type":"boolean","description":"True if `value` is valid."}],"orig":"*\n     * Returns true if the `value` is valid, and updates `invalid`. If you want\n     * your element to have custom validation logic, do not override this method;\n     * override `_getValidity(value)` instead.\n\n     * @param {Object} value The value to be validated. By default, it is passed\n     * to the validator's `validate()` function, if a validator is set.\n     * @return {boolean} True if `value` is valid.\n     "},"function":true,"return":{"type":"boolean","desc":"True if `value` is valid."}},{"__fromBehavior":"Polymer.IronValidatableBehavior","name":"validator","type":"String","desc":"\nName of the validator to use.\n       ","javascriptNode":{"type":"Property","key":{"type":"Identifier","name":"validator","range":[587,596],"loc":{"start":{"line":29,"column":6},"end":{"line":29,"column":15}}},"value":{"type":"ObjectExpression","properties":[{"type":"Property","key":{"type":"Identifier","name":"type","range":[608,612],"loc":{"start":{"line":30,"column":8},"end":{"line":30,"column":12}}},"value":{"type":"Identifier","name":"String","range":[614,620],"loc":{"start":{"line":30,"column":14},"end":{"line":30,"column":20}}},"kind":"init","method":false,"shorthand":false,"computed":false,"range":[608,620],"loc":{"start":{"line":30,"column":8},"end":{"line":30,"column":20}}}],"range":[598,628],"loc":{"start":{"line":29,"column":17},"end":{"line":31,"column":7}}},"kind":"init","method":false,"shorthand":false,"computed":false,"range":[587,628],"loc":{"start":{"line":29,"column":6},"end":{"line":31,"column":7}},"leadingComments":[{"type":"Block","value":"*\n       * Name of the validator to use.\n       ","range":[528,580],"loc":{"start":{"line":26,"column":6},"end":{"line":28,"column":9}}}]},"published":true,"jsdoc":{"description":"\nName of the validator to use.\n       ","tags":[],"orig":"*\n       * Name of the validator to use.\n       "}},{"__fromBehavior":"Polymer.IronValidatableBehavior","name":"validatorType","type":"String","desc":"\nNamespace for this validator.\n       ","javascriptNode":{"type":"Property","key":{"type":"Identifier","name":"validatorType","range":[446,459],"loc":{"start":{"line":21,"column":6},"end":{"line":21,"column":19}}},"value":{"type":"ObjectExpression","properties":[{"type":"Property","key":{"type":"Identifier","name":"type","range":[471,475],"loc":{"start":{"line":22,"column":8},"end":{"line":22,"column":12}}},"value":{"type":"Identifier","name":"String","range":[477,483],"loc":{"start":{"line":22,"column":14},"end":{"line":22,"column":20}}},"kind":"init","method":false,"shorthand":false,"computed":false,"range":[471,483],"loc":{"start":{"line":22,"column":8},"end":{"line":22,"column":20}}},{"type":"Property","key":{"type":"Identifier","name":"value","range":[493,498],"loc":{"start":{"line":23,"column":8},"end":{"line":23,"column":13}}},"value":{"type":"Literal","value":"validator","raw":"'validator'","range":[500,511],"loc":{"start":{"line":23,"column":15},"end":{"line":23,"column":26}}},"kind":"init","method":false,"shorthand":false,"computed":false,"range":[493,511],"loc":{"start":{"line":23,"column":8},"end":{"line":23,"column":26}}}],"range":[461,519],"loc":{"start":{"line":21,"column":21},"end":{"line":24,"column":7}}},"kind":"init","method":false,"shorthand":false,"computed":false,"range":[446,519],"loc":{"start":{"line":21,"column":6},"end":{"line":24,"column":7}},"leadingComments":[{"type":"Block","value":"*\n       * Namespace for this validator.\n       ","range":[387,439],"loc":{"start":{"line":18,"column":6},"end":{"line":20,"column":9}}}]},"published":true,"default":"validator","jsdoc":{"description":"\nNamespace for this validator.\n       ","tags":[],"orig":"*\n       * Namespace for this validator.\n       "}},{"name":"value","type":"String","desc":" Overriden from Polymer.IronFormElementBehavior ","javascriptNode":{"type":"Property","key":{"type":"Identifier","name":"value","range":[1119,1124],"loc":{"start":{"line":43,"column":6},"end":{"line":43,"column":11}}},"value":{"type":"ObjectExpression","properties":[{"type":"Property","key":{"type":"Identifier","name":"type","range":[1136,1140],"loc":{"start":{"line":44,"column":8},"end":{"line":44,"column":12}}},"value":{"type":"Identifier","name":"String","range":[1142,1148],"loc":{"start":{"line":44,"column":14},"end":{"line":44,"column":20}}},"kind":"init","method":false,"shorthand":false,"computed":false,"range":[1136,1148],"loc":{"start":{"line":44,"column":8},"end":{"line":44,"column":20}}},{"type":"Property","key":{"type":"Identifier","name":"value","range":[1158,1163],"loc":{"start":{"line":45,"column":8},"end":{"line":45,"column":13}}},"value":{"type":"Literal","value":"","raw":"''","range":[1165,1167],"loc":{"start":{"line":45,"column":15},"end":{"line":45,"column":17}}},"kind":"init","method":false,"shorthand":false,"computed":false,"range":[1158,1167],"loc":{"start":{"line":45,"column":8},"end":{"line":45,"column":17}}}],"range":[1126,1175],"loc":{"start":{"line":43,"column":13},"end":{"line":46,"column":7}}},"kind":"init","method":false,"shorthand":false,"computed":false,"range":[1119,1175],"loc":{"start":{"line":43,"column":6},"end":{"line":46,"column":7}},"leadingComments":[{"type":"Block","value":" Overriden from Polymer.IronFormElementBehavior ","range":[1060,1112],"loc":{"start":{"line":42,"column":6},"end":{"line":42,"column":58}}}]},"published":true,"default":"","jsdoc":{"description":" Overriden from Polymer.IronFormElementBehavior ","tags":[],"orig":" Overriden from Polymer.IronFormElementBehavior "}},{"name":"_checkedChanged","type":"Function","desc":"\nUpdate the element's value when checked.\n     ","javascriptNode":{"type":"Property","key":{"type":"Identifier","name":"_checkedChanged","range":[1913,1928],"loc":{"start":{"line":75,"column":4},"end":{"line":75,"column":19}}},"value":{"type":"FunctionExpression","id":null,"params":[],"body":{"type":"BlockStatement","body":[{"type":"ExpressionStatement","expression":{"type":"AssignmentExpression","operator":"=","left":{"type":"MemberExpression","computed":false,"object":{"type":"ThisExpression","range":[1949,1953],"loc":{"start":{"line":76,"column":6},"end":{"line":76,"column":10}}},"property":{"type":"Identifier","name":"active","range":[1954,1960],"loc":{"start":{"line":76,"column":11},"end":{"line":76,"column":17}}},"range":[1949,1960],"loc":{"start":{"line":76,"column":6},"end":{"line":76,"column":17}}},"right":{"type":"MemberExpression","computed":false,"object":{"type":"ThisExpression","range":[1963,1967],"loc":{"start":{"line":76,"column":20},"end":{"line":76,"column":24}}},"property":{"type":"Identifier","name":"checked","range":[1968,1975],"loc":{"start":{"line":76,"column":25},"end":{"line":76,"column":32}}},"range":[1963,1975],"loc":{"start":{"line":76,"column":20},"end":{"line":76,"column":32}}},"range":[1949,1975],"loc":{"start":{"line":76,"column":6},"end":{"line":76,"column":32}}},"range":[1949,1976],"loc":{"start":{"line":76,"column":6},"end":{"line":76,"column":33}},"trailingComments":[{"type":"Line","value":" Unless the user has specified a value, a checked element has the","range":[1983,2050],"loc":{"start":{"line":77,"column":6},"end":{"line":77,"column":73}}},{"type":"Line","value":" default value \"on\" when checked.","range":[2057,2092],"loc":{"start":{"line":78,"column":6},"end":{"line":78,"column":41}}}]},{"type":"IfStatement","test":{"type":"BinaryExpression","operator":"===","left":{"type":"MemberExpression","computed":false,"object":{"type":"ThisExpression","range":[2103,2107],"loc":{"start":{"line":79,"column":10},"end":{"line":79,"column":14}}},"property":{"type":"Identifier","name":"value","range":[2108,2113],"loc":{"start":{"line":79,"column":15},"end":{"line":79,"column":20}}},"range":[2103,2113],"loc":{"start":{"line":79,"column":10},"end":{"line":79,"column":20}}},"right":{"type":"Literal","value":"","raw":"''","range":[2118,2120],"loc":{"start":{"line":79,"column":25},"end":{"line":79,"column":27}}},"range":[2103,2120],"loc":{"start":{"line":79,"column":10},"end":{"line":79,"column":27}}},"consequent":{"type":"ExpressionStatement","expression":{"type":"AssignmentExpression","operator":"=","left":{"type":"MemberExpression","computed":false,"object":{"type":"ThisExpression","range":[2130,2134],"loc":{"start":{"line":80,"column":8},"end":{"line":80,"column":12}}},"property":{"type":"Identifier","name":"value","range":[2135,2140],"loc":{"start":{"line":80,"column":13},"end":{"line":80,"column":18}}},"range":[2130,2140],"loc":{"start":{"line":80,"column":8},"end":{"line":80,"column":18}}},"right":{"type":"ConditionalExpression","test":{"type":"MemberExpression","computed":false,"object":{"type":"ThisExpression","range":[2143,2147],"loc":{"start":{"line":80,"column":21},"end":{"line":80,"column":25}}},"property":{"type":"Identifier","name":"checked","range":[2148,2155],"loc":{"start":{"line":80,"column":26},"end":{"line":80,"column":33}}},"range":[2143,2155],"loc":{"start":{"line":80,"column":21},"end":{"line":80,"column":33}}},"consequent":{"type":"Literal","value":"on","raw":"'on'","range":[2158,2162],"loc":{"start":{"line":80,"column":36},"end":{"line":80,"column":40}}},"alternate":{"type":"Literal","value":"","raw":"''","range":[2165,2167],"loc":{"start":{"line":80,"column":43},"end":{"line":80,"column":45}}},"range":[2143,2167],"loc":{"start":{"line":80,"column":21},"end":{"line":80,"column":45}}},"range":[2130,2167],"loc":{"start":{"line":80,"column":8},"end":{"line":80,"column":45}}},"range":[2130,2168],"loc":{"start":{"line":80,"column":8},"end":{"line":80,"column":46}}},"alternate":null,"range":[2099,2168],"loc":{"start":{"line":79,"column":6},"end":{"line":80,"column":46}},"leadingComments":[{"type":"Line","value":" Unless the user has specified a value, a checked element has the","range":[1983,2050],"loc":{"start":{"line":77,"column":6},"end":{"line":77,"column":73}}},{"type":"Line","value":" default value \"on\" when checked.","range":[2057,2092],"loc":{"start":{"line":78,"column":6},"end":{"line":78,"column":41}}}]},{"type":"ExpressionStatement","expression":{"type":"CallExpression","callee":{"type":"MemberExpression","computed":false,"object":{"type":"ThisExpression","range":[2175,2179],"loc":{"start":{"line":81,"column":6},"end":{"line":81,"column":10}}},"property":{"type":"Identifier","name":"fire","range":[2180,2184],"loc":{"start":{"line":81,"column":11},"end":{"line":81,"column":15}}},"range":[2175,2184],"loc":{"start":{"line":81,"column":6},"end":{"line":81,"column":15}}},"arguments":[{"type":"Literal","value":"iron-change","raw":"'iron-change'","range":[2185,2198],"loc":{"start":{"line":81,"column":16},"end":{"line":81,"column":29}}}],"range":[2175,2199],"loc":{"start":{"line":81,"column":6},"end":{"line":81,"column":30}}},"range":[2175,2200],"loc":{"start":{"line":81,"column":6},"end":{"line":81,"column":31}}}],"range":[1941,2206],"loc":{"start":{"line":75,"column":32},"end":{"line":82,"column":5}}},"generator":false,"expression":false,"range":[1930,2206],"loc":{"start":{"line":75,"column":21},"end":{"line":82,"column":5}}},"kind":"init","method":false,"shorthand":false,"computed":false,"range":[1913,2206],"loc":{"start":{"line":75,"column":4},"end":{"line":82,"column":5}},"leadingComments":[{"type":"Block","value":"*\n     * Update the element's value when checked.\n     ","range":[1849,1908],"loc":{"start":{"line":72,"column":4},"end":{"line":74,"column":7}}}]},"params":[],"jsdoc":{"description":"\nUpdate the element's value when checked.\n     ","tags":[],"orig":"*\n     * Update the element's value when checked.\n     "},"private":true,"function":true},{"name":"_getValidity","type":"Function","desc":"\nReturns false if the element is required and not checked, and true otherwise.\n","javascriptNode":{"type":"Property","key":{"type":"Identifier","name":"_getValidity","range":[1449,1461],"loc":{"start":{"line":57,"column":4},"end":{"line":57,"column":16}}},"value":{"type":"FunctionExpression","id":null,"params":[{"type":"Identifier","name":"_value","range":[1472,1478],"loc":{"start":{"line":57,"column":27},"end":{"line":57,"column":33}}}],"body":{"type":"BlockStatement","body":[{"type":"ReturnStatement","argument":{"type":"LogicalExpression","operator":"||","left":{"type":"LogicalExpression","operator":"||","left":{"type":"MemberExpression","computed":false,"object":{"type":"ThisExpression","range":[1495,1499],"loc":{"start":{"line":58,"column":13},"end":{"line":58,"column":17}}},"property":{"type":"Identifier","name":"disabled","range":[1500,1508],"loc":{"start":{"line":58,"column":18},"end":{"line":58,"column":26}}},"range":[1495,1508],"loc":{"start":{"line":58,"column":13},"end":{"line":58,"column":26}}},"right":{"type":"UnaryExpression","operator":"!","argument":{"type":"MemberExpression","computed":false,"object":{"type":"ThisExpression","range":[1513,1517],"loc":{"start":{"line":58,"column":31},"end":{"line":58,"column":35}}},"property":{"type":"Identifier","name":"required","range":[1518,1526],"loc":{"start":{"line":58,"column":36},"end":{"line":58,"column":44}}},"range":[1513,1526],"loc":{"start":{"line":58,"column":31},"end":{"line":58,"column":44}}},"prefix":true,"range":[1512,1526],"loc":{"start":{"line":58,"column":30},"end":{"line":58,"column":44}}},"range":[1495,1526],"loc":{"start":{"line":58,"column":13},"end":{"line":58,"column":44}}},"right":{"type":"LogicalExpression","operator":"&&","left":{"type":"MemberExpression","computed":false,"object":{"type":"ThisExpression","range":[1531,1535],"loc":{"start":{"line":58,"column":49},"end":{"line":58,"column":53}}},"property":{"type":"Identifier","name":"required","range":[1536,1544],"loc":{"start":{"line":58,"column":54},"end":{"line":58,"column":62}}},"range":[1531,1544],"loc":{"start":{"line":58,"column":49},"end":{"line":58,"column":62}}},"right":{"type":"MemberExpression","computed":false,"object":{"type":"ThisExpression","range":[1548,1552],"loc":{"start":{"line":58,"column":66},"end":{"line":58,"column":70}}},"property":{"type":"Identifier","name":"checked","range":[1553,1560],"loc":{"start":{"line":58,"column":71},"end":{"line":58,"column":78}}},"range":[1548,1560],"loc":{"start":{"line":58,"column":66},"end":{"line":58,"column":78}}},"range":[1531,1560],"loc":{"start":{"line":58,"column":49},"end":{"line":58,"column":78}}},"range":[1495,1561],"loc":{"start":{"line":58,"column":13},"end":{"line":58,"column":79}}},"range":[1488,1562],"loc":{"start":{"line":58,"column":6},"end":{"line":58,"column":80}}}],"range":[1480,1568],"loc":{"start":{"line":57,"column":35},"end":{"line":59,"column":5}}},"generator":false,"expression":false,"range":[1463,1568],"loc":{"start":{"line":57,"column":18},"end":{"line":59,"column":5}}},"kind":"init","method":false,"shorthand":false,"computed":false,"range":[1449,1568],"loc":{"start":{"line":57,"column":4},"end":{"line":59,"column":5}},"leadingComments":[{"type":"Block","value":"*\n     * Returns false if the element is required and not checked, and true otherwise.\n     * @return {boolean} true if `required` is false, or if `required` and `checked` are both true.\n     ","range":[1248,1444],"loc":{"start":{"line":53,"column":4},"end":{"line":56,"column":7}}}]},"params":[{"name":"_value"}],"jsdoc":{"description":"\nReturns false if the element is required and not checked, and true otherwise.\n","tags":[{"tag":"return","type":"boolean","description":"true if `required` is false, or if `required` and `checked` are both true."}],"orig":"*\n     * Returns false if the element is required and not checked, and true otherwise.\n     * @return {boolean} true if `required` is false, or if `required` and `checked` are both true.\n     "},"private":true,"function":true,"return":{"type":"boolean","desc":"true if `required` is false, or if `required` and `checked` are both true."}},{"__fromBehavior":"Polymer.IronValidatableBehavior","name":"_invalidChanged","type":"Function","javascriptNode":{"type":"Property","key":{"type":"Identifier","name":"_invalidChanged","range":[1179,1194],"loc":{"start":{"line":61,"column":4},"end":{"line":61,"column":19}}},"value":{"type":"FunctionExpression","id":null,"params":[],"body":{"type":"BlockStatement","body":[{"type":"IfStatement","test":{"type":"MemberExpression","computed":false,"object":{"type":"ThisExpression","range":[1219,1223],"loc":{"start":{"line":62,"column":10},"end":{"line":62,"column":14}}},"property":{"type":"Identifier","name":"invalid","range":[1224,1231],"loc":{"start":{"line":62,"column":15},"end":{"line":62,"column":22}}},"range":[1219,1231],"loc":{"start":{"line":62,"column":10},"end":{"line":62,"column":22}}},"consequent":{"type":"BlockStatement","body":[{"type":"ExpressionStatement","expression":{"type":"CallExpression","callee":{"type":"MemberExpression","computed":false,"object":{"type":"ThisExpression","range":[1243,1247],"loc":{"start":{"line":63,"column":8},"end":{"line":63,"column":12}}},"property":{"type":"Identifier","name":"setAttribute","range":[1248,1260],"loc":{"start":{"line":63,"column":13},"end":{"line":63,"column":25}}},"range":[1243,1260],"loc":{"start":{"line":63,"column":8},"end":{"line":63,"column":25}}},"arguments":[{"type":"Literal","value":"aria-invalid","raw":"'aria-invalid'","range":[1261,1275],"loc":{"start":{"line":63,"column":26},"end":{"line":63,"column":40}}},{"type":"Literal","value":"true","raw":"'true'","range":[1277,1283],"loc":{"start":{"line":63,"column":42},"end":{"line":63,"column":48}}}],"range":[1243,1284],"loc":{"start":{"line":63,"column":8},"end":{"line":63,"column":49}}},"range":[1243,1285],"loc":{"start":{"line":63,"column":8},"end":{"line":63,"column":50}}}],"range":[1233,1293],"loc":{"start":{"line":62,"column":24},"end":{"line":64,"column":7}}},"alternate":{"type":"BlockStatement","body":[{"type":"ExpressionStatement","expression":{"type":"CallExpression","callee":{"type":"MemberExpression","computed":false,"object":{"type":"ThisExpression","range":[1309,1313],"loc":{"start":{"line":65,"column":8},"end":{"line":65,"column":12}}},"property":{"type":"Identifier","name":"removeAttribute","range":[1314,1329],"loc":{"start":{"line":65,"column":13},"end":{"line":65,"column":28}}},"range":[1309,1329],"loc":{"start":{"line":65,"column":8},"end":{"line":65,"column":28}}},"arguments":[{"type":"Literal","value":"aria-invalid","raw":"'aria-invalid'","range":[1330,1344],"loc":{"start":{"line":65,"column":29},"end":{"line":65,"column":43}}}],"range":[1309,1345],"loc":{"start":{"line":65,"column":8},"end":{"line":65,"column":44}}},"range":[1309,1346],"loc":{"start":{"line":65,"column":8},"end":{"line":65,"column":45}}}],"range":[1299,1354],"loc":{"start":{"line":64,"column":13},"end":{"line":66,"column":7}}},"range":[1215,1354],"loc":{"start":{"line":62,"column":6},"end":{"line":66,"column":7}}}],"range":[1207,1360],"loc":{"start":{"line":61,"column":32},"end":{"line":67,"column":5}}},"generator":false,"expression":false,"range":[1196,1360],"loc":{"start":{"line":61,"column":21},"end":{"line":67,"column":5}}},"kind":"init","method":false,"shorthand":false,"computed":false,"range":[1179,1360],"loc":{"start":{"line":61,"column":4},"end":{"line":67,"column":5}}},"params":[],"private":true,"function":true},{"__fromBehavior":"Polymer.IronFormElementBehavior","name":"_parentForm","type":"Object","desc":"\nThe form that the element is registered to.\n       ","javascriptNode":{"type":"Property","key":{"type":"Identifier","name":"_parentForm","range":[1285,1296],"loc":{"start":{"line":55,"column":6},"end":{"line":55,"column":17}}},"value":{"type":"ObjectExpression","properties":[{"type":"Property","key":{"type":"Identifier","name":"type","range":[1308,1312],"loc":{"start":{"line":56,"column":8},"end":{"line":56,"column":12}}},"value":{"type":"Identifier","name":"Object","range":[1314,1320],"loc":{"start":{"line":56,"column":14},"end":{"line":56,"column":20}}},"kind":"init","method":false,"shorthand":false,"computed":false,"range":[1308,1320],"loc":{"start":{"line":56,"column":8},"end":{"line":56,"column":20}}}],"range":[1298,1328],"loc":{"start":{"line":55,"column":19},"end":{"line":57,"column":7}}},"kind":"init","method":false,"shorthand":false,"computed":false,"range":[1285,1328],"loc":{"start":{"line":55,"column":6},"end":{"line":57,"column":7}},"leadingComments":[{"type":"Block","value":"*\n       * The form that the element is registered to.\n       ","range":[1212,1278],"loc":{"start":{"line":52,"column":6},"end":{"line":54,"column":9}}}]},"published":true,"jsdoc":{"description":"\nThe form that the element is registered to.\n       ","tags":[],"orig":"*\n       * The form that the element is registered to.\n       "},"private":true},{"name":"_requiredChanged","type":"Function","desc":"\nUpdate the aria-required label when `required` is changed.\n     ","javascriptNode":{"type":"Property","key":{"type":"Identifier","name":"_requiredChanged","range":[1657,1673],"loc":{"start":{"line":64,"column":4},"end":{"line":64,"column":20}}},"value":{"type":"FunctionExpression","id":null,"params":[],"body":{"type":"BlockStatement","body":[{"type":"IfStatement","test":{"type":"MemberExpression","computed":false,"object":{"type":"ThisExpression","range":[1698,1702],"loc":{"start":{"line":65,"column":10},"end":{"line":65,"column":14}}},"property":{"type":"Identifier","name":"required","range":[1703,1711],"loc":{"start":{"line":65,"column":15},"end":{"line":65,"column":23}}},"range":[1698,1711],"loc":{"start":{"line":65,"column":10},"end":{"line":65,"column":23}}},"consequent":{"type":"BlockStatement","body":[{"type":"ExpressionStatement","expression":{"type":"CallExpression","callee":{"type":"MemberExpression","computed":false,"object":{"type":"ThisExpression","range":[1723,1727],"loc":{"start":{"line":66,"column":8},"end":{"line":66,"column":12}}},"property":{"type":"Identifier","name":"setAttribute","range":[1728,1740],"loc":{"start":{"line":66,"column":13},"end":{"line":66,"column":25}}},"range":[1723,1740],"loc":{"start":{"line":66,"column":8},"end":{"line":66,"column":25}}},"arguments":[{"type":"Literal","value":"aria-required","raw":"'aria-required'","range":[1741,1756],"loc":{"start":{"line":66,"column":26},"end":{"line":66,"column":41}}},{"type":"Literal","value":"true","raw":"'true'","range":[1758,1764],"loc":{"start":{"line":66,"column":43},"end":{"line":66,"column":49}}}],"range":[1723,1765],"loc":{"start":{"line":66,"column":8},"end":{"line":66,"column":50}}},"range":[1723,1766],"loc":{"start":{"line":66,"column":8},"end":{"line":66,"column":51}}}],"range":[1713,1774],"loc":{"start":{"line":65,"column":25},"end":{"line":67,"column":7}}},"alternate":{"type":"BlockStatement","body":[{"type":"ExpressionStatement","expression":{"type":"CallExpression","callee":{"type":"MemberExpression","computed":false,"object":{"type":"ThisExpression","range":[1790,1794],"loc":{"start":{"line":68,"column":8},"end":{"line":68,"column":12}}},"property":{"type":"Identifier","name":"removeAttribute","range":[1795,1810],"loc":{"start":{"line":68,"column":13},"end":{"line":68,"column":28}}},"range":[1790,1810],"loc":{"start":{"line":68,"column":8},"end":{"line":68,"column":28}}},"arguments":[{"type":"Literal","value":"aria-required","raw":"'aria-required'","range":[1811,1826],"loc":{"start":{"line":68,"column":29},"end":{"line":68,"column":44}}}],"range":[1790,1827],"loc":{"start":{"line":68,"column":8},"end":{"line":68,"column":45}}},"range":[1790,1828],"loc":{"start":{"line":68,"column":8},"end":{"line":68,"column":46}}}],"range":[1780,1836],"loc":{"start":{"line":67,"column":13},"end":{"line":69,"column":7}}},"range":[1694,1836],"loc":{"start":{"line":65,"column":6},"end":{"line":69,"column":7}}}],"range":[1686,1842],"loc":{"start":{"line":64,"column":33},"end":{"line":70,"column":5}}},"generator":false,"expression":false,"range":[1675,1842],"loc":{"start":{"line":64,"column":22},"end":{"line":70,"column":5}}},"kind":"init","method":false,"shorthand":false,"computed":false,"range":[1657,1842],"loc":{"start":{"line":64,"column":4},"end":{"line":70,"column":5}},"leadingComments":[{"type":"Block","value":"*\n     * Update the aria-required label when `required` is changed.\n     ","range":[1575,1652],"loc":{"start":{"line":61,"column":4},"end":{"line":63,"column":7}}}]},"params":[],"jsdoc":{"description":"\nUpdate the aria-required label when `required` is changed.\n     ","tags":[],"orig":"*\n     * Update the aria-required label when `required` is changed.\n     "},"private":true,"function":true},{"__fromBehavior":"Polymer.IronValidatableBehavior","name":"_validator","type":"Function","javascriptNode":{"type":"Property","key":{"type":"Identifier","name":"_validator","range":[963,973],"loc":{"start":{"line":53,"column":8},"end":{"line":53,"column":18}}},"value":{"type":"FunctionExpression","id":null,"params":[],"body":{"type":"BlockStatement","body":[{"type":"ReturnStatement","argument":{"type":"LogicalExpression","operator":"&&","left":{"type":"MemberExpression","computed":false,"object":{"type":"ThisExpression","range":[991,995],"loc":{"start":{"line":54,"column":13},"end":{"line":54,"column":17}}},"property":{"type":"Identifier","name":"_validatorMeta","range":[996,1010],"loc":{"start":{"line":54,"column":18},"end":{"line":54,"column":32}}},"range":[991,1010],"loc":{"start":{"line":54,"column":13},"end":{"line":54,"column":32}}},"right":{"type":"CallExpression","callee":{"type":"MemberExpression","computed":false,"object":{"type":"MemberExpression","computed":false,"object":{"type":"ThisExpression","range":[1014,1018],"loc":{"start":{"line":54,"column":36},"end":{"line":54,"column":40}}},"property":{"type":"Identifier","name":"_validatorMeta","range":[1019,1033],"loc":{"start":{"line":54,"column":41},"end":{"line":54,"column":55}}},"range":[1014,1033],"loc":{"start":{"line":54,"column":36},"end":{"line":54,"column":55}}},"property":{"type":"Identifier","name":"byKey","range":[1034,1039],"loc":{"start":{"line":54,"column":56},"end":{"line":54,"column":61}}},"range":[1014,1039],"loc":{"start":{"line":54,"column":36},"end":{"line":54,"column":61}}},"arguments":[{"type":"MemberExpression","computed":false,"object":{"type":"ThisExpression","range":[1040,1044],"loc":{"start":{"line":54,"column":62},"end":{"line":54,"column":66}}},"property":{"type":"Identifier","name":"validator","range":[1045,1054],"loc":{"start":{"line":54,"column":67},"end":{"line":54,"column":76}}},"range":[1040,1054],"loc":{"start":{"line":54,"column":62},"end":{"line":54,"column":76}}}],"range":[1014,1055],"loc":{"start":{"line":54,"column":36},"end":{"line":54,"column":77}}},"range":[991,1055],"loc":{"start":{"line":54,"column":13},"end":{"line":54,"column":77}}},"range":[984,1056],"loc":{"start":{"line":54,"column":6},"end":{"line":54,"column":78}}}],"range":[976,1062],"loc":{"start":{"line":53,"column":21},"end":{"line":55,"column":5}}},"generator":false,"expression":false,"range":[973,1062],"loc":{"start":{"line":53,"column":18},"end":{"line":55,"column":5}}},"kind":"get","method":false,"shorthand":false,"computed":false,"range":[959,1062],"loc":{"start":{"line":53,"column":4},"end":{"line":55,"column":5}}},"params":[],"private":true,"function":true},{"__fromBehavior":"Polymer.IronValidatableBehavior","name":"_validatorMeta","type":"Object","javascriptNode":{"type":"Property","key":{"type":"Identifier","name":"_validatorMeta","range":[841,855],"loc":{"start":{"line":43,"column":6},"end":{"line":43,"column":20}}},"value":{"type":"ObjectExpression","properties":[{"type":"Property","key":{"type":"Identifier","name":"type","range":[867,871],"loc":{"start":{"line":44,"column":8},"end":{"line":44,"column":12}}},"value":{"type":"Identifier","name":"Object","range":[873,879],"loc":{"start":{"line":44,"column":14},"end":{"line":44,"column":20}}},"kind":"init","method":false,"shorthand":false,"computed":false,"range":[867,879],"loc":{"start":{"line":44,"column":8},"end":{"line":44,"column":20}}}],"range":[857,887],"loc":{"start":{"line":43,"column":22},"end":{"line":45,"column":7}}},"kind":"init","method":false,"shorthand":false,"computed":false,"range":[841,887],"loc":{"start":{"line":43,"column":6},"end":{"line":45,"column":7}}},"published":true,"private":true},{"__fromBehavior":"Polymer.IronFormElementBehavior","name":"attached","type":"Function","javascriptNode":{"type":"Property","key":{"type":"Identifier","name":"attached","range":[1341,1349],"loc":{"start":{"line":60,"column":4},"end":{"line":60,"column":12}}},"value":{"type":"FunctionExpression","id":null,"params":[],"body":{"type":"BlockStatement","body":[{"type":"ExpressionStatement","expression":{"type":"CallExpression","callee":{"type":"MemberExpression","computed":false,"object":{"type":"ThisExpression","range":[1508,1512],"loc":{"start":{"line":63,"column":6},"end":{"line":63,"column":10}}},"property":{"type":"Identifier","name":"fire","range":[1513,1517],"loc":{"start":{"line":63,"column":11},"end":{"line":63,"column":15}}},"range":[1508,1517],"loc":{"start":{"line":63,"column":6},"end":{"line":63,"column":15}}},"arguments":[{"type":"Literal","value":"iron-form-element-register","raw":"'iron-form-element-register'","range":[1518,1546],"loc":{"start":{"line":63,"column":16},"end":{"line":63,"column":44}}}],"range":[1508,1547],"loc":{"start":{"line":63,"column":6},"end":{"line":63,"column":45}}},"range":[1508,1548],"loc":{"start":{"line":63,"column":6},"end":{"line":63,"column":46}},"leadingComments":[{"type":"Line","value":" Note: the iron-form that this element belongs to will set this","range":[1370,1435],"loc":{"start":{"line":61,"column":6},"end":{"line":61,"column":71}}},{"type":"Line","value":" element's _parentForm property when handling this event.","range":[1442,1501],"loc":{"start":{"line":62,"column":6},"end":{"line":62,"column":65}}}]}],"range":[1362,1554],"loc":{"start":{"line":60,"column":25},"end":{"line":64,"column":5}}},"generator":false,"expression":false,"range":[1351,1554],"loc":{"start":{"line":60,"column":14},"end":{"line":64,"column":5}}},"kind":"init","method":false,"shorthand":false,"computed":false,"range":[1341,1554],"loc":{"start":{"line":60,"column":4},"end":{"line":64,"column":5}}},"params":[],"private":true,"configuration":true,"function":true},{"__fromBehavior":"Polymer.IronFormElementBehavior","name":"detached","type":"Function","javascriptNode":{"type":"Property","key":{"type":"Identifier","name":"detached","range":[1561,1569],"loc":{"start":{"line":66,"column":4},"end":{"line":66,"column":12}}},"value":{"type":"FunctionExpression","id":null,"params":[],"body":{"type":"BlockStatement","body":[{"type":"IfStatement","test":{"type":"MemberExpression","computed":false,"object":{"type":"ThisExpression","range":[1594,1598],"loc":{"start":{"line":67,"column":10},"end":{"line":67,"column":14}}},"property":{"type":"Identifier","name":"_parentForm","range":[1599,1610],"loc":{"start":{"line":67,"column":15},"end":{"line":67,"column":26}}},"range":[1594,1610],"loc":{"start":{"line":67,"column":10},"end":{"line":67,"column":26}}},"consequent":{"type":"BlockStatement","body":[{"type":"ExpressionStatement","expression":{"type":"CallExpression","callee":{"type":"MemberExpression","computed":false,"object":{"type":"MemberExpression","computed":false,"object":{"type":"ThisExpression","range":[1622,1626],"loc":{"start":{"line":68,"column":8},"end":{"line":68,"column":12}}},"property":{"type":"Identifier","name":"_parentForm","range":[1627,1638],"loc":{"start":{"line":68,"column":13},"end":{"line":68,"column":24}}},"range":[1622,1638],"loc":{"start":{"line":68,"column":8},"end":{"line":68,"column":24}}},"property":{"type":"Identifier","name":"fire","range":[1639,1643],"loc":{"start":{"line":68,"column":25},"end":{"line":68,"column":29}}},"range":[1622,1643],"loc":{"start":{"line":68,"column":8},"end":{"line":68,"column":29}}},"arguments":[{"type":"Literal","value":"iron-form-element-unregister","raw":"'iron-form-element-unregister'","range":[1644,1674],"loc":{"start":{"line":68,"column":30},"end":{"line":68,"column":60}}},{"type":"ObjectExpression","properties":[{"type":"Property","key":{"type":"Identifier","name":"target","range":[1677,1683],"loc":{"start":{"line":68,"column":63},"end":{"line":68,"column":69}}},"value":{"type":"ThisExpression","range":[1685,1689],"loc":{"start":{"line":68,"column":71},"end":{"line":68,"column":75}}},"kind":"init","method":false,"shorthand":false,"computed":false,"range":[1677,1689],"loc":{"start":{"line":68,"column":63},"end":{"line":68,"column":75}}}],"range":[1676,1690],"loc":{"start":{"line":68,"column":62},"end":{"line":68,"column":76}}}],"range":[1622,1691],"loc":{"start":{"line":68,"column":8},"end":{"line":68,"column":77}}},"range":[1622,1692],"loc":{"start":{"line":68,"column":8},"end":{"line":68,"column":78}}}],"range":[1612,1700],"loc":{"start":{"line":67,"column":28},"end":{"line":69,"column":7}}},"alternate":null,"range":[1590,1700],"loc":{"start":{"line":67,"column":6},"end":{"line":69,"column":7}}}],"range":[1582,1706],"loc":{"start":{"line":66,"column":25},"end":{"line":70,"column":5}}},"generator":false,"expression":false,"range":[1571,1706],"loc":{"start":{"line":66,"column":14},"end":{"line":70,"column":5}}},"kind":"init","method":false,"shorthand":false,"computed":false,"range":[1561,1706],"loc":{"start":{"line":66,"column":4},"end":{"line":70,"column":5}}},"params":[],"private":true,"configuration":true,"function":true},{"__fromBehavior":"Polymer.IronValidatableBehavior","name":"ready","type":"Function","javascriptNode":{"type":"Property","key":{"type":"Identifier","name":"ready","range":[1069,1074],"loc":{"start":{"line":57,"column":4},"end":{"line":57,"column":9}}},"value":{"type":"FunctionExpression","id":null,"params":[],"body":{"type":"BlockStatement","body":[{"type":"ExpressionStatement","expression":{"type":"AssignmentExpression","operator":"=","left":{"type":"MemberExpression","computed":false,"object":{"type":"ThisExpression","range":[1095,1099],"loc":{"start":{"line":58,"column":6},"end":{"line":58,"column":10}}},"property":{"type":"Identifier","name":"_validatorMeta","range":[1100,1114],"loc":{"start":{"line":58,"column":11},"end":{"line":58,"column":25}}},"range":[1095,1114],"loc":{"start":{"line":58,"column":6},"end":{"line":58,"column":25}}},"right":{"type":"NewExpression","callee":{"type":"MemberExpression","computed":false,"object":{"type":"Identifier","name":"Polymer","range":[1121,1128],"loc":{"start":{"line":58,"column":32},"end":{"line":58,"column":39}}},"property":{"type":"Identifier","name":"IronMeta","range":[1129,1137],"loc":{"start":{"line":58,"column":40},"end":{"line":58,"column":48}}},"range":[1121,1137],"loc":{"start":{"line":58,"column":32},"end":{"line":58,"column":48}}},"arguments":[{"type":"ObjectExpression","properties":[{"type":"Property","key":{"type":"Identifier","name":"type","range":[1139,1143],"loc":{"start":{"line":58,"column":50},"end":{"line":58,"column":54}}},"value":{"type":"MemberExpression","computed":false,"object":{"type":"ThisExpression","range":[1145,1149],"loc":{"start":{"line":58,"column":56},"end":{"line":58,"column":60}}},"property":{"type":"Identifier","name":"validatorType","range":[1150,1163],"loc":{"start":{"line":58,"column":61},"end":{"line":58,"column":74}}},"range":[1145,1163],"loc":{"start":{"line":58,"column":56},"end":{"line":58,"column":74}}},"kind":"init","method":false,"shorthand":false,"computed":false,"range":[1139,1163],"loc":{"start":{"line":58,"column":50},"end":{"line":58,"column":74}}}],"range":[1138,1164],"loc":{"start":{"line":58,"column":49},"end":{"line":58,"column":75}}}],"range":[1117,1165],"loc":{"start":{"line":58,"column":28},"end":{"line":58,"column":76}}},"range":[1095,1165],"loc":{"start":{"line":58,"column":6},"end":{"line":58,"column":76}}},"range":[1095,1166],"loc":{"start":{"line":58,"column":6},"end":{"line":58,"column":77}}}],"range":[1087,1172],"loc":{"start":{"line":57,"column":22},"end":{"line":59,"column":5}}},"generator":false,"expression":false,"range":[1076,1172],"loc":{"start":{"line":57,"column":11},"end":{"line":59,"column":5}}},"kind":"init","method":false,"shorthand":false,"computed":false,"range":[1069,1172],"loc":{"start":{"line":57,"column":4},"end":{"line":59,"column":5}}},"params":[],"private":true,"configuration":true,"function":true}],"behaviors":["Polymer.IronFormElementBehavior","Polymer.IronValidatableBehavior"],"contentHref":"/var/www/POLYMER/1/2/polymer-element-catalog/bower_components/iron-checked-element-behavior/iron-checked-element-behavior.html"}],"features":[],"elementsByTagName":{}}